[
  {
    "id": "actionsa",
    "short": "ActionSA",
    "name": "ActionSA",
    "descriptionKey": "party.actionsa.desc",
    "ideologyKey": "party.actionsa.ideology",
    "colour": "#009639",
    "website": "https://www.actionsa.org.za/"
  },
  {
    "id": "acdp",
    "short": "ACDP",
    "name": "African Christian Democratic Party",
    "descriptionKey": "party.acdp.desc",
    "ideologyKey": "party.acdp.ideology",
    "colour": "#0088CC",
    "website": "https://acdp.org.za/"
  },
  {
    "id": "anc",
    "short": "ANC",
    "name": "African National Congress",
    "descriptionKey": "party.anc.desc",
    "ideologyKey": "party.anc.ideology",
    "colour": "#008542",
    "website": "https://www.anc1912.org.za/"
  },
  {
    "id": "cope",
    "short": "COPE",
    "name": "Congress of the People",
    "descriptionKey": "party.cope.desc",
    "ideologyKey": "party.cope.ideology",
    "colour": "#1B6CA8",
    "website": "https://cope.org.za/"
  },
  {
    "id": "atm",
    "short": "ATM",
    "name": "African Transformation Movement",
    "descriptionKey": "party.atm.desc",
    "ideologyKey": "party.atm.ideology",
    "colour": "#7B5E8A",
    "website": "https://www.atm-sa.org/"
  },
  {
    "id": "aljama-ah",
    "short": "Al Jama-ah",
    "name": "Al Jama-ah",
    "descriptionKey": "party.aljama-ah.desc",
    "ideologyKey": "party.aljama-ah.ideology",
    "colour": "#00875A",
    "website": "https://www.aljama.co.za/"
  },
  {
    "id": "da",
    "short": "DA",
    "name": "Democratic Alliance",
    "descriptionKey": "party.da.desc",
    "ideologyKey": "party.da.ideology",
    "colour": "#0D5A9C",
    "website": "https://www.da.org.za/"
  },
  {
    "id": "eff",
    "short": "EFF",
    "name": "Economic Freedom Fighters",
    "descriptionKey": "party.eff.desc",
    "ideologyKey": "party.eff.ideology",
    "colour": "#D40000",
    "website": "https://effonline.org/"
  },
  {
    "id": "vfplus",
    "short": "VF+",
    "name": "Freedom Front Plus",
    "nameKey": "party.vfplus.name",
    "descriptionKey": "party.vfplus.desc",
    "ideologyKey": "party.vfplus.ideology",
    "colour": "#E85D00",
    "website": "https://www.vfplus.org.za/"
  },
  {
    "id": "ifp",
    "short": "IFP",
    "name": "Inkatha Freedom Party",
    "descriptionKey": "party.ifp.desc",
    "ideologyKey": "party.ifp.ideology",
    "colour": "#D4A520",
    "website": "https://ifp.org.za/"
  },
  {
    "id": "ncc",
    "short": "NCC",
    "name": "National Coloured Congress",
    "descriptionKey": "party.ncc.desc",
    "ideologyKey": "party.ncc.ideology",
    "colour": "#C85A3C",
    "website": "https://www.nationalcolouredcongress.org.za/"
  },
  {
    "id": "pac",
    "short": "PAC",
    "name": "Pan Africanist Congress of Azania",
    "descriptionKey": "party.pac.desc",
    "ideologyKey": "party.pac.ideology",
    "colour": "#BF9D5C",
    "website": "https://www.pacofazania.org.za/"
  },
  {
    "id": "pa",
    "short": "PA",
    "name": "Patriotic Alliance",
    "descriptionKey": "party.pa.desc",
    "ideologyKey": "party.pa.ideology",
    "colour": "#00A86B",
    "website": "https://mypa.org.za/"
  },
  {
    "id": "sacp",
    "short": "SACP",
    "name": "South African Communist Party",
    "descriptionKey": "party.sacp.desc",
    "ideologyKey": "party.sacp.ideology",
    "colour": "#B30000",
    "website": "https://www.sacp.org.za/"
  },
  {
    "id": "mk",
    "short": "MK",
    "name": "uMkhonto we Sizwe Party",
    "descriptionKey": "party.mk.desc",
    "ideologyKey": "party.mk.ideology",
    "colour": "#1E5A1E",
    "website": "https://mkparty.org.za/"
  },
  {
    "id": "udm",
    "short": "UDM",
    "name": "United Democratic Movement",
    "descriptionKey": "party.udm.desc",
    "ideologyKey": "party.udm.ideology",
    "colour": "#5B8C5A",
    "website": "https://www.udm.org.za/"
  },
  {
    "id": "ufc",
    "short": "UFC",
    "name": "Unite for Change",
    "descriptionKey": "party.ufc.desc",
    "ideologyKey": "party.ufc.ideology",
    "colour": "#E89400",
    "website": "https://www.uniteforchangesa.org/"
  }
]
